{
    "entries": [
        {
            "ID": "2100000000",
            "Height": 2.086432933807373
        },
        {
            "ID": "2100000001",
            "Height": 2.286432981491089
        },
        {
            "ID": "2100000002",
            "Height": 2.502814769744873
        },
        {
            "ID": "2100000003",
            "Height": 4.728621482849121
        },
        {
            "ID": "2100000004",
            "Height": 1.2703311443328858
        },
        {
            "ID": "2100000005",
            "Height": 2.677001714706421
        }
    ]
}